Workbook

Sheet Assumptions
A1: Lab Cost Model – Assumptions
A3: Assumption | B3: Value | C3: Unit / Option | D3: Notes
A4: Training title | B4: DevOps Mastery | C4: Text | D4: Client-facing title
A5: Cloud provider | B5: AWS | C5: AWS / Azure / GCP | D5: Select provider
A6: Region | B6: Mumbai | C6: Mumbai / Central India / GCP Mumbai | D6: Select matching region
A7: Hours per day | B7: 3 | C7: hours | D7: Lab runtime per training day
A8: Training days | B8: 20 | C8: days | D8: Total training days
A9: Participants | B9: 20 | C9: people | D9: Number of learners
A10: Storage GB | B10: 10 | C10: GB | D10: Object storage requirement
A11: Data egress GB | B11: 0 | C11: GB | D11: Estimated outbound transfer
A12: Build minutes | B12: 0 | C12: minutes | D12: CI/CD runner usage
A13: Monitoring GB | B13: 0 | C13: GB | D13: Monitoring/log ingestion
A14: Kubernetes worker nodes | B14: 1 | C14: nodes | D14: Worker count when Kubernetes is used
A15: USD-to-INR rate | B15: 95.56 | C15: INR/USD | D15: Update with current conversion rate
A16: Contingency percentage | B16: 0.1 | C16: % | D16: Risk buffer
A17: GST percentage | B17: 0.18 | C17: % | D17: India GST assumption
A18: Package | B18: Standard | C18: Basic / Standard / Advanced | D18: Controls support pricing
A19: Quote validity | B19: 7 | C19: days | D19: Validity from quote date
A20: Disk GB per VM / worker node | B20: 20 | C20: GB | D20: Explicit sizing assumption; replace with lab-template node sizing when supplied
A21: Applied support rate (INR / participant-day) | B21: =IF(B23="Basic",B24,IF(B23="Standard",B25,B26)) -> 0 | C21: INR / participant-day | D21: Formula selects the applied support tier; total scales with participants and training days
A22: Advanced support threshold | B22: 400 | C22: participant-days | D22: At or above this engagement size, Standard is automatically quoted as Advanced support
A23: Applied support tier | B23: =IF(AND(B18="Standard",B9*B8>=B22),"Advanced",B18) -> Advanced | C23: tier | D23: Uses participant count × training days
A24: Basic support rate | B24: 0 | C24: INR / participant-day | D24: Editable commercial rate
A25: Standard support rate | B25: 0 | C25: INR / participant-day | D25: Editable commercial rate
A26: Advanced support rate | B26: 0 | C26: INR / participant-day | D26: Editable commercial rate
A27: VM profile pricing status | B27: Live profile rates supplied | C27: 2026-09-14T08:10:58.119393+00:00 | D27: Enter vm_profile_rates and vm_profile_sources with current provider URLs before final client approval
A28: Rate snapshot ID | B28: LCQ-C732A86589A14F63BCF04D05FA3BFCFD | C28: audit ID | D28: Use this ID to retrieve the rate snapshot and calculation record
A29: Pricing status | B29: provider_api_verified_public_retail | C29: status | D29: Live SKU rates and official source URLs are required before final client approval
A30: Rate source | B30: https://pricing.us-east-1.amazonaws.com/offers/v1.0/aws/AmazonEC2/current/ap-south-1/index.csv | C30: URL | D30: Official provider pricing page or approved pricing-export URL
A31: Rates checked at (UTC) | B31: 2026-09-14T08:10:58.119393+00:00 | C31: timestamp | D31: Rate snapshot timestamp
A32: Quote valid until (UTC) | B32: 2026-09-21T08:10:58.119393+00:00 | C32: timestamp | D32: Recalculate from current rates after this time
A33: Price-change review threshold | B33: 5 | C33: % | D33: Escalate for review when refreshed pricing changes beyond this threshold
A34: Lab architecture | B34: Proposed learner VMs with shared EKS and 10 GB S3 where required by the TOC. No resources provisioned. Egress, managed build, monitoring and S3 request charges excluded; delete lab resources after each mapped period. | C34: assumption | D34: Quantities are total resources; learner VMs scale with participants, shared services do not
A35: FX status | B35: User-supplied assumption | C35: status | D35: USD/INR is not verified by the cloud price lookup; confirm before approval
A36: Support pricing status | B36: Unconfigured / zero charge | C36: status | D36: No support price is invented. Confirm the applied tier rate before client approval
A37: Quote approval status | B37: Draft — commercial review required | C37: status | D37: Provider verification covers selected resource rates only; confirm architecture, access hours, support, FX, taxes and exclusions

Sheet Rate Card
A1: Rate Card – Editable Provider Pricing
A3: Provider | B3: Region | C3: Resource | D3: Billing unit | E3: USD rate | F3: INR rate | G3: Source URL | H3: Last verified date
A4: AWS | B4: Mumbai | C4: VM | D4: per hour | E4: 0.0448 | F4: =E4*Assumptions!$B$15 -> 4.281088 | G4: https://pricing.us-east-1.amazonaws.com/offers/v1.0/aws/AmazonEC2/current/ap-south-1/index.csv | H4: 2026-09-14T08:10:58.119393+00:00
A5: AWS | B5: Mumbai | C5: Kubernetes control plane | D5: per cluster-hour | E5: 0.1 | F5: =E5*Assumptions!$B$15 -> 9.556 | G5: https://pricing.us-east-1.amazonaws.com/offers/v1.0/aws/AmazonEKS/current/ap-south-1/index.csv | H5: 2026-09-14T08:10:58.119393+00:00
A6: AWS | B6: Mumbai | C6: Kubernetes worker | D6: per VM-hour | E6: 0.1792 | F6: =E6*Assumptions!$B$15 -> 17.124352 | G6: https://pricing.us-east-1.amazonaws.com/offers/v1.0/aws/AmazonEC2/current/ap-south-1/index.csv | H6: 2026-09-14T08:10:58.119393+00:00
A7: AWS | B7: Mumbai | C7: Disk | D7: GB-month | E7: 0.0912 | F7: =E7*Assumptions!$B$15 -> 8.715072 | G7: https://pricing.us-east-1.amazonaws.com/offers/v1.0/aws/AmazonEC2/current/ap-south-1/index.csv | H7: 2026-09-14T08:10:58.119393+00:00
A8: AWS | B8: Mumbai | C8: Storage | D8: GB-month | E8: 0.025 | F8: =E8*Assumptions!$B$15 -> 2.389 | G8: https://pricing.us-east-1.amazonaws.com/offers/v1.0/aws/AmazonS3/current/ap-south-1/index.csv | H8: 2026-09-14T08:10:58.119393+00:00
A9: AWS | B9: Mumbai | C9: Egress | D9: per GB | E9: 0 | F9: =E9*Assumptions!$B$15 -> 0 | G9: https://aws.amazon.com/pricing/ | H9: 2026-09-14T08:10:58.119393+00:00
A10: AWS | B10: Mumbai | C10: Build runner | D10: per build minute | E10: 0 | F10: =E10*Assumptions!$B$15 -> 0 | G10: https://aws.amazon.com/pricing/ | H10: 2026-09-14T08:10:58.119393+00:00
A11: AWS | B11: Mumbai | C11: Managed database | D11: per hour | E11: 0 | F11: =E11*Assumptions!$B$15 -> 0 | G11: https://aws.amazon.com/pricing/ | H11: 2026-09-14T08:10:58.119393+00:00
A12: AWS | B12: Mumbai | C12: Monitoring | D12: per GB | E12: 0 | F12: =E12*Assumptions!$B$15 -> 0 | G12: https://aws.amazon.com/pricing/ | H12: 2026-09-14T08:10:58.119393+00:00
A13: Azure | B13: Central India | C13: VM | D13: per hour | G13: https://azure.microsoft.com/pricing/details/virtual-machines/ | H13: Not priced for this quote
A14: Azure | B14: Central India | C14: Kubernetes control plane | D14: per cluster-hour | G14: https://azure.microsoft.com/pricing/details/kubernetes-service/ | H14: Not priced for this quote
A15: Azure | B15: Central India | C15: Kubernetes worker | D15: per VM-hour | G15: https://azure.microsoft.com/pricing/details/virtual-machines/ | H15: Not priced for this quote
A16: Azure | B16: Central India | C16: Disk | D16: GB-month | G16: https://azure.microsoft.com/pricing/details/managed-disks/ | H16: Not priced for this quote
A17: Azure | B17: Central India | C17: Storage | D17: GB-month | G17: https://azure.microsoft.com/pricing/details/storage/blobs/ | H17: Not priced for this quote
A18: Azure | B18: Central India | C18: Egress | D18: per GB | G18: https://azure.microsoft.com/pricing/details/bandwidth/ | H18: Not priced for this quote
A19: Azure | B19: Central India | C19: Build runner | D19: per build minute | G19: https://azure.microsoft.com/pricing/details/devops/azure-devops-services/ | H19: Not priced for this quote
A20: Azure | B20: Central India | C20: Managed database | D20: per hour | G20: https://azure.microsoft.com/pricing/details/azure-sql-database/ | H20: Not priced for this quote
A21: Azure | B21: Central India | C21: Monitoring | D21: per GB | G21: https://azure.microsoft.com/pricing/details/monitor/ | H21: Not priced for this quote
A22: GCP | B22: GCP Mumbai | C22: VM | D22: per hour | G22: https://cloud.google.com/compute/vm-instance-pricing | H22: Not priced for this quote
A23: GCP | B23: GCP Mumbai | C23: Kubernetes control plane | D23: per cluster-hour | G23: https://cloud.google.com/kubernetes-engine/pricing | H23: Not priced for this quote
A24: GCP | B24: GCP Mumbai | C24: Kubernetes worker | D24: per VM-hour | G24: https://cloud.google.com/compute/vm-instance-pricing | H24: Not priced for this quote
... A30: GCP | B30: GCP Mumbai | C30: Monitoring | D30: per GB | G30: https://cloud.google.com/stackdriver/pricing | H30: Not priced for this quote
A31: AWS | B31: Mumbai | C31: VM Light | D31: per hour | E31: 0.0448 | F31: =E31*Assumptions!$B$15 -> 4.281088 | G31: https://pricing.us-east-1.amazonaws.com/offers/v1.0/aws/AmazonEC2/current/ap-south-1/index.csv | H31: 2026-09-14T08:10:58.119393+00:00
A32: AWS | B32: Mumbai | C32: VM Heavy | D32: per hour | E32: 0.1792 | F32: =E32*Assumptions!$B$15 -> 17.124352 | G32: https://pricing.us-east-1.amazonaws.com/offers/v1.0/aws/AmazonEC2/current/ap-south-1/index.csv | H32: 2026-09-14T08:10:58.119393+00:00

Sheet TOC Mapping
A1: Training TOC → Infrastructure Mapping
A3: Day | B3: Training topic | C3: VM qty | D3: VM profile | E3: K8s control plane | F3: K8s worker nodes | G3: Managed DB | H3: Object storage | I3: Active days
A4: 1 | B4: DevOps Orientation, SDLC and Agile Delivery | C4: 20 | D4: Heavy | E4: 0 | F4: 0 | G4: 0 | H4: 0 | I4: 1
A5: 2 | B5: Linux Fundamentals for DevOps | C5: 20 | D5: Light | E5: 0 | F5: 0 | G5: 0 | H5: 0 | I5: 1
A6: 3 | B6: Shell Scripting and Automation | C6: 20 | D6: Light | E6: 0 | F6: 0 | G6: 0 | H6: 0 | I6: 1
A7: 4 | B7: Networking, SSH and Web Basics | C7: 20 | D7: Light | E7: 0 | F7: 0 | G7: 0 | H7: 0 | I7: 1
A8: 5 | B8: Git and GitHub Collaboration | C8: 20 | D8: Light | E8: 0 | F8: 0 | G8: 0 | H8: 0 | I8: 1
A9: 6 | B9: Build Tools and Artifact Management | C9: 20 | D9: Light | E9: 0 | F9: 0 | G9: 0 | H9: 0 | I9: 1
A10: 7 | B10: Jenkins Fundamentals | C10: 20 | D10: Heavy | E10: 0 | F10: 0 | G10: 0 | H10: 0 | I10: 1
A11: 8 | B11: Jenkins Pipeline as Code | C11: 20 | D11: Heavy | E11: 0 | F11: 0 | G11: 0 | H11: 0 | I11: 1
A12: 9 | B12: GitHub Actions and GitLab CI | C12: 20 | D12: Light | E12: 0 | F12: 0 | G12: 0 | H12: 0 | I12: 1
A13: 10 | B13: Docker Fundamentals | C13: 20 | D13: Heavy | E13: 0 | F13: 0 | G13: 0 | H13: 0 | I13: 1
A14: 11 | B14: Docker Compose and Multi-Container Apps | C14: 20 | D14: Heavy | E14: 0 | F14: 0 | G14: 0 | H14: 0 | I14: 1
A15: 12 | B15: Container Registry and Image Security | C15: 20 | D15: Heavy | E15: 0 | F15: 0 | G15: 0 | H15: 0 | I15: 1
... A23: 20 | B23: Capstone Demo and Certification Roadmap | C23: 20 | D23: Heavy | E23: 0 | F23: 0 | G23: 0 | H23: 0 | I23: 1
A25: Mapping note
A26: Use this sheet to map every training day to the infrastructure it needs. Resource Cost Breakdown calculates each resource with its own billing unit; do not force a single generic cost formula across VM, storage, egress, build, or Kubernetes. VM Light and Heavy rows are billed separately from the Rate Card; active days prevent multi-day labs from being under-counted.

Sheet Resource Cost Breakdown
A1: Resource Cost Breakdown – Billing-Unit Based
A3: Resource | B3: Quantity | C3: Billing unit | D3: Rate (INR) | E3: Usage driver | F3: Days / Hours | G3: Formula basis | H3: Total (INR) | I3: Provider | J3: Region
A4: VM (profiled) | B4: =SUMPRODUCT('TOC Mapping'!$C$4:$C$23,'TOC Mapping'!$I$4:$I$23) -> 400 | C4: per hour | D4: =SUMIFS('Rate Card'!$F$4:$F$30,'Rate Card'!$A$4:$A$30,I4,'Rate Card'!$B$4:$B$30,J4,'Rate Card'!$C$4:$C$30,A4) -> 0 | E4: runtime hours | F4: =Assumptions!$B$7 -> 3 | G4: Light/Heavy VM-days × respective rate × Hours/day | H4: =(SUMPRODUCT('TOC Mapping'!$C$4:$C$23,'TOC Mapping'!$I$4:$I$23,--('TOC Mapping'!$D$4:$D$23="Light"))*'Rate Card'!$F$31+SUMPRODUCT('TOC Mapping'!$C$4:$C$23,'TOC Mapping'!$I$4:$I$23,--('TOC Mapping'!$D$4:$D$23="Heavy"))*'Rate Card'!$F$32)*Assumptions!$B$7 -> 14384.456 | I4: =Assumptions!$B$5 -> AWS | J4: =Assumptions!$B$6 -> Mumbai
A5: Kubernetes control plane | B5: =SUMPRODUCT('TOC Mapping'!$E$4:$E$23,'TOC Mapping'!$I$4:$I$23) -> 1 | C5: per cluster-hour | D5: =SUMIFS('Rate Card'!$F$4:$F$30,'Rate Card'!$A$4:$A$30,I5,'Rate Card'!$B$4:$B$30,J5,'Rate Card'!$C$4:$C$30,A5) -> 9.556 | E5: runtime hours | F5: =Assumptions!$B$7 -> 3 | G5: Resource-days × Rate × Hours/day | H5: =B5*D5*F5 -> 28.668 | I5: =Assumptions!$B$5 -> AWS | J5: =Assumptions!$B$6 -> Mumbai
A6: Kubernetes worker | B6: =SUMPRODUCT('TOC Mapping'!$F$4:$F$23,'TOC Mapping'!$I$4:$I$23) -> 1 | C6: per VM-hour | D6: =SUMIFS('Rate Card'!$F$4:$F$30,'Rate Card'!$A$4:$A$30,I6,'Rate Card'!$B$4:$B$30,J6,'Rate Card'!$C$4:$C$30,A6) -> 17.124352 | E6: runtime hours | F6: =Assumptions!$B$7 -> 3 | G6: Resource-days × Rate × Hours/day | H6: =B6*D6*F6 -> 51.373056 | I6: =Assumptions!$B$5 -> AWS | J6: =Assumptions!$B$6 -> Mumbai
A7: Disk | B7: =SUMPRODUCT(('TOC Mapping'!$C$4:$C$23+'TOC Mapping'!$F$4:$F$23),'TOC Mapping'!$I$4:$I$23)*Assumptions!$B$20 -> 8020 | C7: GB-month | D7: =SUMIFS('Rate Card'!$F$4:$F$30,'Rate Card'!$A$4:$A$30,I7,'Rate Card'!$B$4:$B$30,J7,'Rate Card'!$C$4:$C$30,A7) -> 8.715072 | E7: prorated days | F7: 1 | G7: GB-node-days × monthly rate / 30 | H7: =B7*D7/30 -> 2329.8292 | I7: =Assumptions!$B$5 -> AWS | J7: =Assumptions!$B$6 -> Mumbai
A8: Storage | B8: =SUMPRODUCT('TOC Mapping'!$H$4:$H$23,'TOC Mapping'!$I$4:$I$23) -> 10 | C8: GB-month | D8: =SUMIFS('Rate Card'!$F$4:$F$30,'Rate Card'!$A$4:$A$30,I8,'Rate Card'!$B$4:$B$30,J8,'Rate Card'!$C$4:$C$30,A8) -> 2.389 | E8: prorated days | F8: 1 | G8: GB-days × monthly rate / 30 | H8: =B8*D8/30 -> 0.79633333 | I8: =Assumptions!$B$5 -> AWS | J8: =Assumptions!$B$6 -> Mumbai
A9: Egress | B9: =Assumptions!B11 -> 0 | C9: per GB | D9: =SUMIFS('Rate Card'!$F$4:$F$30,'Rate Card'!$A$4:$A$30,I9,'Rate Card'!$B$4:$B$30,J9,'Rate Card'!$C$4:$C$30,A9) -> 0 | E9: one-time | F9: 1 | G9: GB × Rate | H9: =B9*D9 -> 0 | I9: =Assumptions!$B$5 -> AWS | J9: =Assumptions!$B$6 -> Mumbai
A10: Build runner | B10: =Assumptions!B12 -> 0 | C10: per build minute | D10: =SUMIFS('Rate Card'!$F$4:$F$30,'Rate Card'!$A$4:$A$30,I10,'Rate Card'!$B$4:$B$30,J10,'Rate Card'!$C$4:$C$30,A10) -> 0 | E10: one-time | F10: 1 | G10: Minutes × Rate | H10: =B10*D10 -> 0 | I10: =Assumptions!$B$5 -> AWS | J10: =Assumptions!$B$6 -> Mumbai
A11: Managed database | B11: =SUMPRODUCT('TOC Mapping'!$G$4:$G$23,'TOC Mapping'!$I$4:$I$23) -> 0 | C11: per hour | D11: =SUMIFS('Rate Card'!$F$4:$F$30,'Rate Card'!$A$4:$A$30,I11,'Rate Card'!$B$4:$B$30,J11,'Rate Card'!$C$4:$C$30,A11) -> 0 | E11: runtime hours | F11: =Assumptions!$B$7 -> 3 | G11: Resource-days × Rate × Hours/day | H11: =B11*D11*F11 -> 0 | I11: =Assumptions!$B$5 -> AWS | J11: =Assumptions!$B$6 -> Mumbai
A12: Monitoring | B12: =Assumptions!B13 -> 0 | C12: per GB | D12: =SUMIFS('Rate Card'!$F$4:$F$30,'Rate Card'!$A$4:$A$30,I12,'Rate Card'!$B$4:$B$30,J12,'Rate Card'!$C$4:$C$30,A12) -> 0 | E12: one-time | F12: 1 | G12: GB × Rate | H12: =B12*D12 -> 0 | I12: =Assumptions!$B$5 -> AWS | J12: =Assumptions!$B$6 -> Mumbai
A14: Total Infrastructure Cost | H14: =SUM(H4:H12) -> 16795.122

Sheet Client Estimate
A1: Client Lab Cost Estimate
A3: CLIENT QUOTE SUMMARY
A4: Training title | B4: =Assumptions!B4 -> DevOps Mastery
A5: Cloud provider and region | B5: =Assumptions!B5&" – "&Assumptions!B6 -> AWS – Mumbai
A6: Number of participants | B6: =Assumptions!B9 -> 20
A7: Training days and hours/day | B7: =Assumptions!B8&" days × "&Assumptions!B7&" hours/day" -> 20 days × 3 hours/day
A8: Infrastructure cost | B8: ='Resource Cost Breakdown'!H14 -> 16795.122
A9: Support cost | B9: =Assumptions!B21*Assumptions!B9*Assumptions!B8 -> 0
A10: Contingency | B10: =(B8+B9)*Assumptions!B16 -> 1679.5122
A11: Tax / GST | B11: =(B8+B9+B10)*Assumptions!B17 -> 3325.4342
A12: Final estimated cost | B12: =B8+B9+B10+B11 -> 21800.069
A13: Cost per participant | B13: =B12/Assumptions!B9 -> 1090.0034
A14: Quote validity | B14: =Assumptions!B19&" days from quote date" -> 7 days from quote date
A16: Estimate notes
A17: Fresh public retail rates checked: 2026-09-14T08:10:58.119393+00:00. Valid until: 2026-09-21T08:10:58.119393+00:00. Price-change review: not triggered. See Live Price Check. Account discounts and future usage may differ.

Sheet Live Price Check
A1: Resource | B1: SKU | C1: Billing dimension | D1: Unit | E1: USD rate | F1: Region | G1: Source | H1: Checked at | I1: Previous USD rate | J1: Change % | K1: Review required
A2: VM | B2: 4NK2QE2HS7XC4TZC | C2: 4NK2QE2HS7XC4TZC.JRTCKXETXF.6YS6EN2CT7 | D2: Hrs | E2: 0.0448 | F2: Mumbai | G2: https://pricing.us-east-1.amazonaws.com/offers/v1.0/aws/AmazonEC2/current/ap-south-1/index.csv | H2: 2026-09-14T08:10:58.119393+00:00 | I2: 0.0448 | J2: 0 | K2: No
A3: VM Light | B3: 4NK2QE2HS7XC4TZC | C3: 4NK2QE2HS7XC4TZC.JRTCKXETXF.6YS6EN2CT7 | D3: Hrs | E3: 0.0448 | F3: Mumbai | G3: https://pricing.us-east-1.amazonaws.com/offers/v1.0/aws/AmazonEC2/current/ap-south-1/index.csv | H3: 2026-09-14T08:10:58.119393+00:00 | I3: 0.0448 | J3: 0 | K3: No
A4: VM Heavy | B4: WSEUB4NX5HQYMN3K | C4: WSEUB4NX5HQYMN3K.JRTCKXETXF.6YS6EN2CT7 | D4: Hrs | E4: 0.1792 | F4: Mumbai | G4: https://pricing.us-east-1.amazonaws.com/offers/v1.0/aws/AmazonEC2/current/ap-south-1/index.csv | H4: 2026-09-14T08:10:58.119393+00:00 | I4: 0.1792 | J4: 0 | K4: No
A5: Kubernetes control plane | B5: RQJ9MJY8F5PSNNWU | C5: RQJ9MJY8F5PSNNWU.JRTCKXETXF.6YS6EN2CT7 | D5: Hours | E5: 0.1 | F5: Mumbai | G5: https://pricing.us-east-1.amazonaws.com/offers/v1.0/aws/AmazonEKS/current/ap-south-1/index.csv | H5: 2026-09-14T08:10:58.119393+00:00 | I5: 0.1 | J5: 0 | K5: No
A6: Kubernetes worker | B6: WSEUB4NX5HQYMN3K | C6: WSEUB4NX5HQYMN3K.JRTCKXETXF.6YS6EN2CT7 | D6: Hrs | E6: 0.1792 | F6: Mumbai | G6: https://pricing.us-east-1.amazonaws.com/offers/v1.0/aws/AmazonEC2/current/ap-south-1/index.csv | H6: 2026-09-14T08:10:58.119393+00:00 | I6: 0.1792 | J6: 0 | K6: No
A7: Disk | B7: D7RMW443YWTMZ4V5 | C7: D7RMW443YWTMZ4V5.JRTCKXETXF.6YS6EN2CT7 | D7: GB-Mo | E7: 0.0912 | F7: Mumbai | G7: https://pricing.us-east-1.amazonaws.com/offers/v1.0/aws/AmazonEC2/current/ap-south-1/index.csv | H7: 2026-09-14T08:10:58.119393+00:00 | I7: 0.0912 | J7: 0 | K7: No
A8: Storage | B8: USGUTP2JY23N9GH2 | C8: USGUTP2JY23N9GH2.JRTCKXETXF.PGHJ3S3EYE | D8: GB-Mo | E8: 0.025 | F8: Mumbai | G8: https://pricing.us-east-1.amazonaws.com/offers/v1.0/aws/AmazonS3/current/ap-south-1/index.csv | H8: 2026-09-14T08:10:58.119393+00:00 | I8: 0.025 | J8: 0 | K8: No
A9: Egress | B9: NOT_BILLED | C9: not-enabled | D9: 1 GB | E9: 0 | F9: Mumbai | G9: https://aws.amazon.com/pricing/ | H9: 2026-09-14T08:10:58.119393+00:00 | I9: 0 | K9: No
A10: Build runner | B10: NOT_BILLED | C10: not-enabled | D10: minutes | E10: 0 | F10: Mumbai | G10: https://aws.amazon.com/pricing/ | H10: 2026-09-14T08:10:58.119393+00:00 | I10: 0 | K10: No
A11: Managed database | B11: NOT_BILLED | C11: not-enabled | D11: 1 Hour | E11: 0 | F11: Mumbai | G11: https://aws.amazon.com/pricing/ | H11: 2026-09-14T08:10:58.119393+00:00 | I11: 0 | K11: No
A12: Monitoring | B12: NOT_BILLED | C12: not-enabled | D12: 1 GB | E12: 0 | F12: Mumbai | G12: https://aws.amazon.com/pricing/ | H12: 2026-09-14T08:10:58.119393+00:00 | I12: 0 | K12: No
