Workbook

Sheet Client Summary
A1: DevOps Lab Cost Estimate
A2: Client quote summary — verified public retail rates. Provider alternatives are shown separately and must not be added together.
A4: AWS | Mumbai
A5: Training title | B5: ='Lab Cost Estimate'!B25
A6: Participants | B6: ='Lab Cost Estimate'!B27
A7: Training duration | B7: ='Lab Cost Estimate'!B28
A8: Infrastructure cost | B8: ='Lab Cost Estimate'!B29
A9: Support cost | B9: ='Lab Cost Estimate'!B30
A10: Contingency | B10: ='Lab Cost Estimate'!B31
A11: Tax / GST | B11: ='Lab Cost Estimate'!B32
A12: Final estimated cost | B12: ='Lab Cost Estimate'!B33
A13: Cost per participant | B13: ='Lab Cost Estimate'!B34
A14: Quote validity | B14: ='Lab Cost Estimate'!B35
A16: Included documents
A17: • Trainer profile
A18: • Training ToC
A19: • Detailed resource cost, assumptions, and verified rate card

Sheet Lab Cost Estimate
A1: Cloud lab cost estimate
A2: Provider totals are separate. Use the cloud(s) required by the course; do not add alternatives.
A4: AWS — Resource Cost Breakdown
A5: Resource Cost Breakdown – Billing-Unit Based
A7: Resource | B7: Quantity | C7: Billing unit | D7: Rate (INR) | E7: Usage driver | F7: Days / Hours | G7: Formula basis | H7: Total (INR) | I7: Provider | J7: Region
A8: VM (profiled) | B8: =SUMPRODUCT($C$161:$C$180,$I$161:$I$180) | C8: per hour | D8: =SUMIFS($F$126:$F$152,$A$126:$A$152,I8,$B$126:$B$152,J8,$C$126:$C$152,A8) | E8: runtime hours | F8: =$B$89 | G8: Light/Heavy VM-days × respective rate × Hours/day | H8: =(SUMPRODUCT($C$161:$C$180,$I$161:$I$180,--($D$161:$D$180="Light"))*$F$153+SUMPRODUCT($C$161:$C$180,$I$161:$I$180,--($D$161:$D$180="Heavy"))*$F$154)*$B$89 | I8: =$B$87 | J8: =$B$88
A9: Kubernetes control plane | B9: =SUMPRODUCT($E$161:$E$180,$I$161:$I$180) | C9: per cluster-hour | D9: =SUMIFS($F$126:$F$152,$A$126:$A$152,I9,$B$126:$B$152,J9,$C$126:$C$152,A9) | E9: runtime hours | F9: =$B$89 | G9: Resource-days × Rate × Hours/day | H9: =B9*D9*F9 | I9: =$B$87 | J9: =$B$88
A10: Kubernetes worker | B10: =SUMPRODUCT($F$161:$F$180,$I$161:$I$180) | C10: per VM-hour | D10: =SUMIFS($F$126:$F$152,$A$126:$A$152,I10,$B$126:$B$152,J10,$C$126:$C$152,A10) | E10: runtime hours | F10: =$B$89 | G10: Resource-days × Rate × Hours/day | H10: =B10*D10*F10 | I10: =$B$87 | J10: =$B$88
A11: Disk | B11: =SUMPRODUCT(($C$161:$C$180+$F$161:$F$180),$I$161:$I$180)*$B$102 | C11: GB-month | D11: =SUMIFS($F$126:$F$152,$A$126:$A$152,I11,$B$126:$B$152,J11,$C$126:$C$152,A11) | E11: prorated days | F11: 1 | G11: GB-node-days × monthly rate / 30 | H11: =B11*D11/30 | I11: =$B$87 | J11: =$B$88
A12: Storage | B12: =SUMPRODUCT($H$161:$H$180,$I$161:$I$180) | C12: GB-month | D12: =SUMIFS($F$126:$F$152,$A$126:$A$152,I12,$B$126:$B$152,J12,$C$126:$C$152,A12) | E12: prorated days | F12: 1 | G12: GB-days × monthly rate / 30 | H12: =B12*D12/30 | I12: =$B$87 | J12: =$B$88
A13: Egress | B13: =B93 | C13: per GB | D13: =SUMIFS($F$126:$F$152,$A$126:$A$152,I13,$B$126:$B$152,J13,$C$126:$C$152,A13) | E13: one-time | F13: 1 | G13: GB × Rate | H13: =B13*D13 | I13: =$B$87 | J13: =$B$88
A14: Build runner | B14: =B94 | C14: per build minute | D14: =SUMIFS($F$126:$F$152,$A$126:$A$152,I14,$B$126:$B$152,J14,$C$126:$C$152,A14) | E14: one-time | F14: 1 | G14: Minutes × Rate | H14: =B14*D14 | I14: =$B$87 | J14: =$B$88
A15: Managed database | B15: =SUMPRODUCT($G$161:$G$180,$I$161:$I$180) | C15: per hour | D15: =SUMIFS($F$126:$F$152,$A$126:$A$152,I15,$B$126:$B$152,J15,$C$126:$C$152,A15) | E15: runtime hours | F15: =$B$89 | G15: Resource-days × Rate × Hours/day | H15: =B15*D15*F15 | I15: =$B$87 | J15: =$B$88
A16: Monitoring | B16: =B95 | C16: per GB | D16: =SUMIFS($F$126:$F$152,$A$126:$A$152,I16,$B$126:$B$152,J16,$C$126:$C$152,A16) | E16: one-time | F16: 1 | G16: GB × Rate | H16: =B16*D16 | I16: =$B$87 | J16: =$B$88
A18: Total Infrastructure Cost | H18: =SUM(H8:H16)
A21: AWS — Client Estimate
A22: Client Lab Cost Estimate
A24: CLIENT QUOTE SUMMARY
A25: Training title | B25: =B86
A26: Cloud provider and region | B26: =B87&" – "&B88
A27: Number of participants | B27: =B91
A28: Training days and hours/day | B28: =B90&" days × "&B89&" hours/day"
A29: Infrastructure cost | B29: =H18
A30: Support cost | B30: =B103*B91*B90
A31: Contingency | B31: =(B29+B30)*B98
A32: Tax / GST | B32: =(B29+B30+B31)*B99
A33: Final estimated cost | B33: =B29+B30+B31+B32
A34: Cost per participant | B34: =B33/B91
A35: Quote validity | B35: =B101&" days from quote date"
A37: Estimate notes
A38: Fresh public retail rates checked: 2026-09-15T09:05:32.395861+00:00. Valid until: 2026-09-22T09:05:32.395861+00:00. Price-change review: not triggered. See Live Price Check. Account discounts and future usage may differ.
A43: AZURE — Resource Cost Breakdown
A44: Resource Cost Breakdown – Billing-Unit Based
A46: Resource | B46: Quantity | C46: Billing unit | D46: Rate (INR) | E46: Usage driver | F46: Days / Hours | G46: Formula basis | H46: Total (INR) | I46: Provider | J46: Region
A47: VM (profiled) | B47: =SUMPRODUCT($C$281:$C$300,$I$281:$I$300) | C47: per hour | D47: =SUMIFS($F$246:$F$272,$A$246:$A$272,I47,$B$246:$B$272,J47,$C$246:$C$272,A47) | E47: runtime hours | F47: =$B$209 | G47: Light/Heavy VM-days × respective rate × Hours/day | H47: =(SUMPRODUCT($C$281:$C$300,$I$281:$I$300,--($D$281:$D$300="Light"))*$F$273+SUMPRODUCT($C$281:$C$300,$I$281:$I$300,--($D$281:$D$300="Heavy"))*$F$274)*$B$209 | I47: =$B$207 | J47: =$B$208
A48: Kubernetes control plane | B48: =SUMPRODUCT($E$281:$E$300,$I$281:$I$300) | C48: per cluster-hour | D48: =SUMIFS($F$246:$F$272,$A$246:$A$272,I48,$B$246:$B$272,J48,$C$246:$C$272,A48) | E48: runtime hours | F48: =$B$209 | G48: Resource-days × Rate × Hours/day | H48: =B48*D48*F48 | I48: =$B$207 | J48: =$B$208
A49: Kubernetes worker | B49: =SUMPRODUCT($F$281:$F$300,$I$281:$I$300) | C49: per VM-hour | D49: =SUMIFS($F$246:$F$272,$A$246:$A$272,I49,$B$246:$B$272,J49,$C$246:$C$272,A49) | E49: runtime hours | F49: =$B$209 | G49: Resource-days × Rate × Hours/day | H49: =B49*D49*F49 | I49: =$B$207 | J49: =$B$208
A50: Disk | B50: =SUMPRODUCT(($C$281:$C$300+$F$281:$F$300),$I$281:$I$300)*$B$222 | C50: GB-month | D50: =SUMIFS($F$246:$F$272,$A$246:$A$272,I50,$B$246:$B$272,J50,$C$246:$C$272,A50) | E50: prorated days | F50: 1 | G50: GB-node-days × monthly rate / 30 | H50: =B50*D50/30 | I50: =$B$207 | J50: =$B$208
A51: Storage | B51: =SUMPRODUCT($H$281:$H$300,$I$281:$I$300) | C51: GB-month | D51: =SUMIFS($F$246:$F$272,$A$246:$A$272,I51,$B$246:$B$272,J51,$C$246:$C$272,A51) | E51: prorated days | F51: 1 | G51: GB-days × monthly rate / 30 | H51: =B51*D51/30 | I51: =$B$207 | J51: =$B$208
A52: Egress | B52: =B213 | C52: per GB | D52: =SUMIFS($F$246:$F$272,$A$246:$A$272,I52,$B$246:$B$272,J52,$C$246:$C$272,A52) | E52: one-time | F52: 1 | G52: GB × Rate | H52: =B52*D52 | I52: =$B$207 | J52: =$B$208
A53: Build runner | B53: =B214 | C53: per build minute | D53: =SUMIFS($F$246:$F$272,$A$246:$A$272,I53,$B$246:$B$272,J53,$C$246:$C$272,A53) | E53: one-time | F53: 1 | G53: Minutes × Rate | H53: =B53*D53 | I53: =$B$207 | J53: =$B$208
A54: Managed database | B54: =SUMPRODUCT($G$281:$G$300,$I$281:$I$300) | C54: per hour | D54: =SUMIFS($F$246:$F$272,$A$246:$A$272,I54,$B$246:$B$272,J54,$C$246:$C$272,A54) | E54: runtime hours | F54: =$B$209 | G54: Resource-days × Rate × Hours/day | H54: =B54*D54*F54 | I54: =$B$207 | J54: =$B$208
A55: Monitoring | B55: =B215 | C55: per GB | D55: =SUMIFS($F$246:$F$272,$A$246:$A$272,I55,$B$246:$B$272,J55,$C$246:$C$272,A55) | E55: one-time | F55: 1 | G55: GB × Rate | H55: =B55*D55 | I55: =$B$207 | J55: =$B$208
A57: Total Infrastructure Cost | H57: =SUM(H47:H55)
A60: AZURE — Client Estimate
A61: Client Lab Cost Estimate
A63: CLIENT QUOTE SUMMARY
A64: Training title | B64: =B206
A65: Cloud provider and region | B65: =B207&" – "&B208
A66: Number of participants | B66: =B211
A67: Training days and hours/day | B67: =B210&" days × "&B209&" hours/day"
A68: Infrastructure cost | B68: =H57
A69: Support cost | B69: =B223*B211*B210
A70: Contingency | B70: =(B68+B69)*B218
A71: Tax / GST | B71: =(B68+B69+B70)*B219
A72: Final estimated cost | B72: =B68+B69+B70+B71
A73: Cost per participant | B73: =B72/B211
A74: Quote validity | B74: =B221&" days from quote date"
A76: Estimate notes
A77: Fresh public retail rates checked: 2026-09-15T09:05:38.277193+00:00. Valid until: 2026-09-22T09:05:38.277193+00:00. Price-change review: not triggered. See Live Price Check. Account discounts and future usage may differ.
A82: AWS — Assumptions
A83: Lab Cost Model – Assumptions
A85: Assumption | B85: Value | C85: Unit / Option | D85: Notes
A86: Training title | B86: DevOps Mastery | C86: Text | D86: Client-facing title
A87: Cloud provider | B87: AWS | C87: AWS / Azure / GCP | D87: Select provider
A88: Region | B88: Mumbai | C88: Mumbai / Central India / GCP Mumbai | D88: Select matching region
A89: Hours per day | B89: 3 | C89: hours | D89: Lab runtime per training day
A90: Training days | B90: 20 | C90: days | D90: Total training days
A91: Participants | B91: 34 | C91: people | D91: Number of learners
A92: Storage GB | B92: 10 | C92: GB | D92: Object storage requirement
A93: Data egress GB | B93: 0 | C93: GB | D93: Estimated outbound transfer
A94: Build minutes | B94: 0 | C94: minutes | D94: CI/CD runner usage
A95: Monitoring GB | B95: 0 | C95: GB | D95: Monitoring/log ingestion
A96: Kubernetes worker nodes | B96: 1 | C96: nodes | D96: Worker count when Kubernetes is used
A97: USD-to-INR rate | B97: 95.56 | C97: INR/USD | D97: Update with current conversion rate
A98: Contingency percentage | B98: 0.1 | C98: % | D98: Risk buffer
A99: GST percentage | B99: 0.18 | C99: % | D99: India GST assumption
A100: Package | B100: Standard | C100: Basic / Standard / Advanced | D100: Controls support pricing
A101: Quote validity | B101: 7 | C101: days | D101: Validity from quote date
A102: Disk GB per VM / worker node | B102: 20 | C102: GB | D102: Explicit sizing assumption; replace with lab-template node sizing when supplied
A103: Applied support rate (INR / participant-day) | B103: =IF(B105="Basic",B106,IF(B105="Standard",B107,B108)) | C103: INR / participant-day | D103: Formula selects the applied support tier; total scales with participants and training days
A104: Advanced support threshold | B104: 400 | C104: participant-days | D104: At or above this engagement size, Standard is automatically quoted as Advanced support
A105: Applied support tier | B105: =IF(AND(B100="Standard",B91*B90>=B104),"Advanced",B100) | C105: tier | D105: Uses participant count × training days
A106: Basic support rate | B106: 0 | C106: INR / participant-day | D106: Editable commercial rate
A107: Standard support rate | B107: 0 | C107: INR / participant-day | D107: Editable commercial rate
A108: Advanced support rate | B108: 0 | C108: INR / participant-day | D108: Editable commercial rate
A109: VM profile pricing status | B109: Live profile rates supplied | C109: 2026-09-15T09:05:32.395861+00:00 | D109: Enter vm_profile_rates and vm_profile_sources with current provider URLs before final client approval
A110: Rate snapshot ID | B110: LCQ-F7258247C914450F8AF0968F2B54C55C | C110: audit ID | D110: Use this ID to retrieve the rate snapshot and calculation record
A111: Pricing status | B111: provider_api_verified_public_retail | C111: status | D111: Live SKU rates and official source URLs are required before final client approval
A112: Rate source | B112: https://pricing.us-east-1.amazonaws.com/offers/v1.0/aws/AmazonEC2/current/ap-south-1/index.csv | C112: URL | D112: Official provider pricing page or approved pricing-export URL
A113: Rates checked at (UTC) | B113: 2026-09-15T09:05:32.395861+00:00 | C113: timestamp | D113: Rate snapshot timestamp
A114: Quote valid until (UTC) | B114: 2026-09-22T09:05:32.395861+00:00 | C114: timestamp | D114: Recalculate from current rates after this time
A115: Price-change review threshold | B115: 5 | C115: % | D115: Escalate for review when refreshed pricing changes beyond this threshold
A116: Lab architecture | B116: Caller-supplied per-day resource mapping | C116: assumption | D116: Quantities are total resources; learner VMs scale with participants, shared services do not
A117: FX status | B117: User-supplied assumption | C117: status | D117: USD/INR is not verified by the cloud price lookup; confirm before approval
A118: Support pricing status | B118: Unconfigured / zero charge | C118: status | D118: No support price is invented. Confirm the applied tier rate before client approval
A119: Quote approval status | B119: Draft — commercial review required | C119: status | D119: Provider verification covers selected resource rates only; confirm architecture, access hours, support, FX, taxes and exclusions
A122: AWS — Rate Card
A123: Rate Card – Editable Provider Pricing
A125: Provider | B125: Region | C125: Resource | D125: Billing unit | E125: USD rate | F125: INR rate | G125: Source URL | H125: Last verified date
...
